{
  "project_info": {
    "project_number": "412161370131",
    "firebase_url": "https://gofit-7036c-default-rtdb.firebaseio.com",
    "project_id": "gofit-7036c",
    "storage_bucket": "gofit-7036c.appspot.com"
  },
  "client": [
    {
      "client_info": {
        "mobilesdk_app_id": "1:412161370131:android:3c5686cdf14e939a9fb7e6",
        "android_client_info": {
          "package_name": "com.gofit.app"
        }
      },
      "oauth_client": [],
      "api_key": [
        {
          "current_key": "AIzaSyCrfbuJJ0EQRQHAmiLCjOEld85Y5SCjfTQ"
        }
      ],
      "services": {
        "appinvite_service": {
          "other_platform_oauth_client": []
        }
      }
    }
  ],
  "configuration_version": "1"
}